pydfs_lineup_optimizer_enhanced/__init__.py
pydfs_lineup_optimizer_enhanced/constants.py
pydfs_lineup_optimizer_enhanced/context.py
pydfs_lineup_optimizer_enhanced/exceptions.py
pydfs_lineup_optimizer_enhanced/exposure_strategy.py
pydfs_lineup_optimizer_enhanced/fantasy_points_strategy.py
pydfs_lineup_optimizer_enhanced/lineup.py
pydfs_lineup_optimizer_enhanced/lineup_exporter.py
pydfs_lineup_optimizer_enhanced/lineup_importer.py
pydfs_lineup_optimizer_enhanced/lineup_optimizer.py
pydfs_lineup_optimizer_enhanced/lineup_printer.py
pydfs_lineup_optimizer_enhanced/player.py
pydfs_lineup_optimizer_enhanced/player_pool.py
pydfs_lineup_optimizer_enhanced/rules.py
pydfs_lineup_optimizer_enhanced/settings.py
pydfs_lineup_optimizer_enhanced/stacks.py
pydfs_lineup_optimizer_enhanced/statistics.py
pydfs_lineup_optimizer_enhanced/tz.py
pydfs_lineup_optimizer_enhanced/utils.py
pydfs_lineup_optimizer_enhanced/version.py
pydfs_lineup_optimizer_enhanced/sites/__init__.py
pydfs_lineup_optimizer_enhanced/sites/sites_registry.py
pydfs_lineup_optimizer_enhanced/sites/draftkings/__init__.py
pydfs_lineup_optimizer_enhanced/sites/draftkings/captain_mode/__init__.py
pydfs_lineup_optimizer_enhanced/sites/draftkings/captain_mode/importer.py
pydfs_lineup_optimizer_enhanced/sites/draftkings/captain_mode/settings.py
pydfs_lineup_optimizer_enhanced/sites/draftkings/classic/__init__.py
pydfs_lineup_optimizer_enhanced/sites/draftkings/classic/importer.py
pydfs_lineup_optimizer_enhanced/sites/draftkings/classic/settings.py
pydfs_lineup_optimizer_enhanced/sites/draftkings/tiers/__init__.py
pydfs_lineup_optimizer_enhanced/sites/draftkings/tiers/importer.py
pydfs_lineup_optimizer_enhanced/sites/draftkings/tiers/settings.py
pydfs_lineup_optimizer_enhanced/sites/fanball/__init__.py
pydfs_lineup_optimizer_enhanced/sites/fanball/settings.py
pydfs_lineup_optimizer_enhanced/sites/fanduel/__init__.py
pydfs_lineup_optimizer_enhanced/sites/fanduel/classic/__init__.py
pydfs_lineup_optimizer_enhanced-4.0.2.dist-info/licenses/LICENSE
pydfs_lineup_optimizer_enhanced-4.0.2.dist-info/METADATA
pydfs_lineup_optimizer_enhanced-4.0.2.dist-info/WHEEL
pydfs_lineup_optimizer_enhanced-4.0.2.dist-info/top_level.txt
pydfs_lineup_optimizer_enhanced-4.0.2.dist-info/RECORD
