Metadata-Version: 2.4
Name: pydfs-lineup-optimizer-enhanced
Version: 4.0.2
Summary: Tool for creating optimal lineups for daily fantasy sports
Home-page: https://github.com/Edamijueda/pydfs-lineup-optimizer-enhanced
Author: Edamijueda
Author-email: tobbyzomo221@gmail.com
License: MIT
Keywords: dfs,fantasy,sport,lineup,optimize,optimizer,nba,nfl,nhl,mlb
Classifier: Development Status :: 4 - Beta
Classifier: Environment :: Console
Classifier: Intended Audience :: End Users/Desktop
Classifier: Intended Audience :: Developers
Classifier: Operating System :: POSIX
Classifier: Programming Language :: Python
License-File: LICENSE
Requires-Dist: PuLP==2.4
Requires-Dist: pytz>=2020.5
Dynamic: author
Dynamic: author-email
Dynamic: classifier
Dynamic: description
Dynamic: description-content-type
Dynamic: home-page
Dynamic: keywords
Dynamic: license
Dynamic: license-file
Dynamic: requires-dist
Dynamic: summary
